atlasapprox/__init__.py
atlasapprox/exceptions.py
atlasapprox/utils.py
atlasapprox-0.2.4.dist-info/LICENSE.txt
atlasapprox-0.2.4.dist-info/METADATA
atlasapprox-0.2.4.dist-info/WHEEL
atlasapprox-0.2.4.dist-info/top_level.txt
atlasapprox-0.2.4.dist-info/RECORD
