Metadata-Version: 2.1
Name: atlasapprox
Version: 0.2.4
Summary: Cell atlas approximations, Python API
Home-page: https://apidocs.atlasapprox.org
Author: Fabio Zanini
Author-email: Fabio Zanini <fabio.zanini@unsw.edu.au>
License: Copyright 2024 Fabio Zanini
Project-URL: Homepage, https://atlasapprox.org
Project-URL: Documentation, https://atlasapprox.readthedocs.io
Project-URL: Repository, https://github.com/fabilab/cell_atlas_approximations_API
Project-URL: Bug Tracker, https://github.com/fabilab/cell_atlas_approximations_API/issues
Keywords: single cell,cell atlas,omics,biology
Platform: ALL
Classifier: Development Status :: 4 - Beta
Classifier: Intended Audience :: Developers
Classifier: Intended Audience :: Science/Research
Classifier: Programming Language :: Python :: 3
Classifier: Programming Language :: Python :: 3.7
Classifier: Programming Language :: Python :: 3.8
Classifier: Programming Language :: Python :: 3.9
Classifier: Programming Language :: Python :: 3.10
Classifier: Programming Language :: Python :: 3.11
Classifier: Programming Language :: Python :: 3 :: Only
Classifier: Topic :: Scientific/Engineering
Classifier: Topic :: Scientific/Engineering :: Bio-Informatics
Classifier: Topic :: Software Development :: Libraries :: Python Modules
Requires-Python: >=3.8
License-File: LICENSE.txt
Requires-Dist: requests
Requires-Dist: numpy
Requires-Dist: pandas
Provides-Extra: plotting
Requires-Dist: matplotlib ; extra == 'plotting'
Requires-Dist: seaborn ; extra == 'plotting'
